LICENSE
README.md
setup.py
pyclimonitor/__init__.py
pyclimonitor/__main__.py
pyclimonitor/setup.py
pyclimonitor.egg-info/PKG-INFO
pyclimonitor.egg-info/SOURCES.txt
pyclimonitor.egg-info/dependency_links.txt
pyclimonitor.egg-info/requires.txt
pyclimonitor.egg-info/top_level.txt